{
  "mode": "pre",
  "tag": "beta",
  "initialVersions": {
    "@elog/cli": "0.2.2",
    "@elog/core": "0.2.2",
    "@elog/deploy": "0.2.2",
    "@elog/plugin-adapter": "0.2.2",
    "@elog/plugin-image": "0.2.2",
    "@elog/sdk-notion": "0.2.2",
    "@elog/sdk-yuque": "0.2.2",
    "@elog/shared": "0.2.2",
    "yuque-confluence": "1.0.0",
    "yuque-default": "1.0.0",
    "@elog/sdk-confluence": "0.2.2"
  },
  "changesets": [
    "angry-badgers-enjoy",
    "brown-ducks-unite",
    "fair-plants-enjoy",
    "gentle-years-change",
    "new-snails-admire",
    "odd-shoes-whisper",
    "rare-emus-attack",
    "shy-bobcats-remain",
    "thick-pears-whisper"
  ]
}
